dash_core_components/__init__.py
dash_core_components/express.py
dash_core_components-2.0.0.dist-info/LICENSE
dash_core_components-2.0.0.dist-info/METADATA
dash_core_components-2.0.0.dist-info/WHEEL
dash_core_components-2.0.0.dist-info/top_level.txt
dash_core_components-2.0.0.dist-info/RECORD
