Metadata-Version: 2.1
Name: dash_core_components
Version: 2.0.0
Summary: Core component suite for Dash
Home-page: UNKNOWN
Author: Chris Parmer <chris@plotly.com>
Author-email: chris@plotly.com
License: MIT
Platform: UNKNOWN
